CHANGES.rst
MANIFEST.in
README.rst
config.example.yml
setup.py
bin/pycbox
pycbox/__init__.py
pycbox.egg-info/PKG-INFO
pycbox.egg-info/SOURCES.txt
pycbox.egg-info/dependency_links.txt
pycbox.egg-info/not-zip-safe
pycbox.egg-info/requires.txt
pycbox.egg-info/top_level.txt
pycbox/static/folder.png
pycbox/static/highlight.png
pycbox/static/save.png
pycbox/static/style.css
pycbox/static/view.png
pycbox/templates/base.html
pycbox/templates/gallery.html
pycbox/templates/index.html
pycbox/templates/upload.html